TrofimovLib/Tree.cpython-313-x86_64-linux-gnu.so
TrofimovLib/Tree.pyi
TrofimovLib/__init__.py
TrofimovLib/py.typed
trofimovlib-1.0.3.dist-info/METADATA
trofimovlib-1.0.3.dist-info/WHEEL
trofimovlib-1.0.3.dist-info/top_level.txt
trofimovlib-1.0.3.dist-info/RECORD
